main.py
whoami_mcp-0.1.0.dist-info/licenses/LICENSE
whoami_mcp-0.1.0.dist-info/METADATA
whoami_mcp-0.1.0.dist-info/WHEEL
whoami_mcp-0.1.0.dist-info/top_level.txt
whoami_mcp-0.1.0.dist-info/RECORD
