Metadata-Version: 2.4
Name: whoami-mcp
Version: 0.1.0
Summary: Add your description here
Requires-Python: >=3.13
License-File: LICENSE
Requires-Dist: mcp[cli]>=1.4.1
Dynamic: license-file
